raspberry_wifi_scanner/__init__.py
raspberry_wifi_scanner/calculations.py
raspberry_wifi_scanner/data_collection.py
raspberry_wifi_scanner/dataframe_functions.py
raspberry_wifi_scanner/definitions.py
raspberry_wifi_scanner/plotting.py
raspberry_wifi_scanner-0.1.0.dist-info/licenses/LICENSE
raspberry_wifi_scanner-0.1.0.dist-info/METADATA
raspberry_wifi_scanner-0.1.0.dist-info/WHEEL
raspberry_wifi_scanner-0.1.0.dist-info/top_level.txt
raspberry_wifi_scanner-0.1.0.dist-info/RECORD
