Metadata-Version: 2.4
Name: raspberry-wifi-scanner
Version: 0.1.0
Summary: Scanning Local Wi-Fi Networks with Raspberry Pi
Author-email: Caleb Yourison <caleb.yourison@gmail.com>
License: MIT License
Project-URL: homepage, https://github.com/calebyourison/raspberry_scanner
Keywords: raspberry,wifi,scan
Classifier: Development Status :: 3 - Alpha
Classifier: Programming Language :: Python :: 3
Requires-Python: >=3.9
License-File: LICENSE
Requires-Dist: numpy>=2.0.0
Requires-Dist: pandas>=2.0.0
Requires-Dist: plotly>=6.0.0
Requires-Dist: template-log-parser>=0.8.0
Dynamic: license-file
